practice5/tmips1_2/top.v
/*
 * From D. M. Harris and S. L. Harris, "Digital Design and Computer Architecture"
 */
`timescale 1ns / 1ps
 // rename for your .dat-file
`define DATFILE "sample1.dat"

module dmem(
    input  clk, we,
    input  [31:0] a, wd,
    output [31:0] rd);

   reg [31:0] RAM[63:0];
   assign rd = RAM[a[31:2]];
	
   always @ (posedge clk)
     if (we)
       RAM[a[31:2]] <= wd;

   initial
     begin
	$readmemh (`DATFILE, RAM);
     end

endmodule

module imem (
    input  [5:0]  a,
    output [31:0] rd);
				
   reg [31:0]  RAM[63:0];
	
   initial
     begin
	$readmemh (`DATFILE, RAM);
     end
		
   assign rd = RAM[a];
endmodule

module top(
    input clk,
    input reset,
    output [31:0] writedata,
    output [31:0] dataaddr,
    output memwrite
    );

   wire [31:0] pc, instr, readdata;
   // instantiate a processor and memories
   mips mips (clk, reset, pc, instr, memwrite, dataaddr, writedata, readdata);
   imem imem (pc[7:2], instr);
   dmem dmem (clk, memwrite, dataaddr, writedata, readdata);
	
endmodule

tmips/alu.v
/*
 * From D. M. Harris and S. L. Harris, "Digital Design and Computer Architecture"
 */
`timescale 1ns / 1ps
module alu(
    input [31:0] srca,
    input [31:0] srcb,
    input [3:0] alucontrol,
    output reg [31:0] aluout,
    output reg zero
    );

   always @ (*)
     begin
	case (alucontrol)
	  4'b0000: aluout <= srca & srcb;
	  4'b0001: aluout <= srca | srcb;
	  4'b0010: aluout <= srca + srcb;
	  4'b0110: aluout <= srca - srcb;
     4'b1100: aluout <= ~(srca | srcb);
	  4'b0111: aluout <= (srca-srcb)>>31;
	endcase
	zero <= (srca == srcb) ? 1 : 0;
     end
	
endmodule

module alutest;

   reg [31:0] opa, opb;
   reg [3:0]  aluc;
   wire [31:0] res;
   wire        zero;
   11
   alu alu1(opa, opb, aluc, res, zero);

   initial begin
      $dumpfile("alutest.vcd");
      $dumpvars(0, alutest);

      opa = 3; opb = -6; aluc = 0; #1
      aluc = 1; #1
      aluc = 2; #1
      aluc = 6; #1
      aluc = 7; #1
      aluc = 12; #1
      $finish;
   end
   

endmodule // alutest

tmips/datapath.v
/*
 * From D. M. Harris and S. L. Harris, "Digital Design and Computer Architecture"
 */
`timescale 1ns / 1ps
module adder(
    input  [31:0] a, b,
    output [31:0] y);

   assign y = a + b;
endmodule

module sl2 (
    input  [31:0] a,
    output [31:0] y);
				
   assign y = {a[29:00], 2'b00};
endmodule

module signext (
    input  [15:0] a,
    output [31:0] y);
					
   assign y = {{16{a[15]}}, a};
endmodule

module zeroext (
    input  [15:0] a,
    output [31:0] y);
					
   assign y = {16'b0, a};
endmodule

module sethi (
    input  [15:0] a,
    output [31:0] y);
					
   assign y = {a, 16'b0};
endmodule

// immtype:
//  - 00 signext
//  - 01 zeroext
//  - 10 sethi
module immext (
    input  [1:0] immtype,
    input  [15:0] a,
    output [31:0] y);

   wire [31:0] ysignext;
   wire [31:0] yzeroext;
   wire [31:0] ysethi;

   signext  se(a, ysignext);
   zeroext  ze(a, yzeroext);
   sethi    sh(a, ysethi);

   assign y = immtype[1] ? ysethi
	      : (immtype[0] ? yzeroext : ysignext);
   
endmodule

module flopr # (parameter WIDTH = 8)
   (input	clk, reset,
    input	[WIDTH-1:0] d,
    output reg [WIDTH-1:0]  q);
					
   always @ (posedge clk, posedge reset)
     if (reset) q <= 0;
     else	q <= d;
endmodule

module mux2 # (parameter WIDTH = 8)
   (input  [WIDTH-1:0] d0, d1,
    input  s,
    output [WIDTH-1:0] y);
				
   assign y = s ? d1 : d0;
endmodule

module regfile(
    input clk,
    input we3,
    input [4:0] ra1,
    input [4:0] ra2,
    input [4:0] wa3,
    input [31:0] wd3,
    output [31:0] rd1,
    output [31:0] rd2
    );

   reg [31:0] 	  rf[31:0];
	
   // 3-port register file
   always @ (posedge clk)
     if (we3) rf[wa3] <= wd3;
		
   assign rd1 = (ra1 != 0) ? rf[ra1] : 0;
   assign rd2 = (ra2 != 0) ? rf[ra2] : 0;
endmodule

module datapath(
    input  clk,
    input  reset,
    input  memtoreg,
    input  pcsrc,
    input  alusrc,
    input  regdst,
    input  [1:0] immtype,
    input  regwrite,
    input  jump,
    input  [3:0] alucontrol,
    output zero,
    output [31:0] pc,
    input  [31:0] instr,
    output [31:0] aluout,
    output [31:0] writedata,
    input  [31:0] readdata
    );

   wire [4:0] 	 writereg;
   wire [31:0] 	 pcnext, pcnextbr, pcplus4, pcbranch;
   wire [31:0] 	 immextv, signimmsh;
   wire [31:0] 	 srca, srcb;
   wire [31:0] 	 result;
	
   // for next PC
   flopr #(32)	pcreg(clk, reset, pcnext, pc);
   adder	pcadd1 (pc, 32'b100, pcplus4);
   sl2		immsh(immextv, signimmsh);
   adder	pcadd2(pcplus4, signimmsh, pcbranch);
   mux2 #(32)   pcbrmux(pcplus4, pcbranch, pcsrc, pcnextbr);
   mux2 #(32)   pcmux(pcnextbr, {pcplus4[31:28], instr[25:0], 2'b00},
		      jump, pcnext);
							
   // reg-file logic
   regfile	rf(clk, regwrite, instr[25:21], instr[20:16], writereg,
		   result, srca, writedata);
   mux2 #(5)	wrmux(instr[20:16], instr[15:11], regdst, writereg);
   mux2 #(32)	resmux(aluout, readdata, memtoreg, result);
   immext	ie(immtype, instr[15:0], immextv);
	
   // ALU logic
   mux2 #(32) srcbmux(writedata, immextv, alusrc, srcb);
   alu alu(srca, srcb, alucontrol, aluout, zero);
endmodule

tmips/controller.v
/*
 * From D. M. Harris and S. L. Harris, "Digital Design and Computer Architecture"
 */
`timescale 1ns / 1ps
module maindec(
    input [5:0] op,
    output memtoreg,
    output memwrite,
    output branch,
    output alusrc,
    output regdst,
    output [1:0] immtype,
    output regwrite,
    output jump,
    output [2:0] aluop
    );

   reg [11:0] 	 controls;
	
   assign { regwrite, immtype, regdst, alusrc, branch, memwrite,
	    memtoreg, jump, aluop } = controls;
				
   always @ (*)
     case (op)
       6'b000000: controls <= 12'b100100000100; //Rtype
       6'b100011: controls <= 12'b100010010000; //LW
       6'b101011: controls <= 12'b000010100000; //SW
       6'b000100: controls <= 12'b000001000001; //BEQ
       6'b001000: controls <= 12'b100010000000; //ADDI
       6'b001111: controls <= 12'b110010000011; //LUI
       6'b001101: controls <= 12'b101010000011; //ORI
       6'b000010: controls <= 12'b000000001000; //J
       default:   controls <= 12'bxxxxxxxxxxxx; //???
     endcase

endmodule

module aludec(
    input [5:0] funct,
    input [2:0] aluop,
    output reg [3:0] alucontrol
    );

   always @ (*)
     case (aluop)
        3'b000: alucontrol <= 4'b0010; // addition
        3'b001: alucontrol <= 4'b0110; // subtraction
        3'b011: alucontrol <= 4'b0001; // or
        default: case (funct) // Rtype (aluop is 100)
          6'b100000: alucontrol <= 4'b0010; //ADD
          6'b100010: alucontrol <= 4'b0110; //SUB
          6'b100100: alucontrol <= 4'b0000; //AND
          6'b100101: alucontrol <= 4'b0001; //OR
          6'b101010: alucontrol <= 4'b0111; //SLT
          default:   alucontrol <= 4'bxxxx; //???
        endcase
     endcase
endmodule

module controller(
    input [5:0] op,
    input [5:0] funct,
    input zero,
    output memtoreg,
    output memwrite,
    output pcsrc,
    output alusrc,
    output regdst,
    output [1:0] immtype, 
    output regwrite,
    output jump,
    output [3:0] alucontrol
    );

   wire [2:0] 	 aluop;
   wire 	 branch;
	
   maindec md (op, memtoreg, memwrite, branch, alusrc,
	       regdst, immtype, regwrite, jump, aluop);
   aludec ad (funct, aluop, alucontrol);
	
   assign pcsrc = branch & zero;
endmodule

module testcont;
   reg [5:0] op;
   reg [5:0] funct;
   reg 	     zero;
   wire      memtoreg, memwrite, pcsrc, alusrc, regdst, regwrite, jump;
   wire [1:0] immtype;
   wire [3:0] alucontrol;

   controller ctl(op, funct, zero, memtoreg, memwrite, pcsrc,
		  alusrc, regdst, immtype, regwrite, jump, alucontrol);

   initial begin
      $dumpfile("testcont.vcd");
      $dumpvars(0, testcont);
      zero = 0; op = 0; funct = 'h20; #1
      op = 'h2b #1
      op = 'h04 #1
      op = 'h08 #1
      op = 'h02 #1
      $finish;
   end
endmodule // testcont

practice5/tmips1_1/mips.v
/*
 * From D. M. Harris and S. L. Harris, "Digital Design and Computer Architecture"
 */
`timescale 1ns / 1ps
module mips(
    input  clk,
    input  reset,
    output [31:0] pc,
    input  [31:0] instr,
    output memwrite,
    output [31:0] aluout,
    output [31:0] writedata,
    input  [31:0] readdata
    );

   wire 	  memtoreg, branch, alusrc, regdst, regwrite, jump, zero;
   wire [1:0] 	  immtype;
 	  
   wire [3:0] 	  alucontrol;
	
   controller ctl(instr[31:26], instr[5:0], zero, memtoreg, memwrite, pcsrc,
		  alusrc, regdst, immtype, regwrite, jump, alucontrol);
   datapath dp(clk, reset, memtoreg, pcsrc, alusrc, regdst, immtype, regwrite,
	       jump, alucontrol, zero, pc, instr, aluout, writedata, readdata);
					
endmodule

tmips/testbench.v
/*
 * From D. M. Harris and S. L. Harris, "Digital Design and Computer Architecture"
 */
`timescale 1ns / 1ps
module testbench();

   reg	clk;
   reg	reset;
	
   wire [31:0] writedata, dataaddr;
   wire        memwrite;
	
   // instantiate device to be tested
   top dut (clk, reset, writedata, dataaddr, memwrite);
	
   // initialize test
   initial begin
      $dumpfile("testb.vcd");
      $dumpvars(0, testbench);
      reset <= 1; # 22; reset <= 0;
   end
		
   // generate clock to sequence tests
   always
     begin
	clk <= 1; #5; clk <= 0; #5;
     end
		
   // check results
   always @ (negedge clk)
     begin
	if (memwrite) begin
	   if (dataaddr === 84 & writedata === 7) begin
	      $display ("Simulation succeeded");
	      $finish;
	   end else if (dataaddr === 84) begin
	      $display ("Simulation failed");
	      $finish;
	   end
	end
     end

endmodule

tmips/testb.vcd
$date
	Mon Oct 14 13:41:54 2019
$end
$version
	Icarus Verilog
$end
$timescale
	1ps
$end
$scope module testbench $end
$var wire 32 ! writedata [31:0] $end
$var wire 1 " memwrite $end
$var wire 32 # dataaddr [31:0] $end
$var reg 1 $ clk $end
$var reg 1 % reset $end
$scope module dut $end
$var wire 1 $ clk $end
$var wire 1 % reset $end
$var wire 32 & writedata [31:0] $end
$var wire 32 ' readdata [31:0] $end
$var wire 32 ( pc [31:0] $end
$var wire 1 " memwrite $end
$var wire 32 ) instr [31:0] $end
$var wire 32 * dataaddr [31:0] $end
$scope module dmem $end
$var wire 1 $ clk $end
$var wire 32 + rd [31:0] $end
$var wire 1 " we $end
$var wire 32 , wd [31:0] $end
$var wire 32 - a [31:0] $end
$upscope $end
$scope module imem $end
$var wire 6 . a [5:0] $end
$var wire 32 / rd [31:0] $end
$upscope $end
$scope module mips $end
$var wire 1 $ clk $end
$var wire 32 0 instr [31:0] $end
$var wire 32 1 readdata [31:0] $end
$var wire 1 % reset $end
$var wire 1 2 zero $end
$var wire 32 3 writedata [31:0] $end
$var wire 1 4 regwrite $end
$var wire 1 5 regdst $end
$var wire 1 6 pcsrc $end
$var wire 32 7 pc [31:0] $end
$var wire 1 " memwrite $end
$var wire 1 8 memtoreg $end
$var wire 1 9 jump $end
$var wire 2 : immtype [1:0] $end
$var wire 1 ; alusrc $end
$var wire 32 < aluout [31:0] $end
$var wire 4 = alucontrol [3:0] $end
$scope module ctl $end
$var wire 6 > funct [5:0] $end
$var wire 6 ? op [5:0] $end
$var wire 1 6 pcsrc $end
$var wire 1 2 zero $end
$var wire 1 4 regwrite $end
$var wire 1 5 regdst $end
$var wire 1 " memwrite $end
$var wire 1 8 memtoreg $end
$var wire 1 9 jump $end
$var wire 2 @ immtype [1:0] $end
$var wire 1 A branch $end
$var wire 1 ; alusrc $end
$var wire 3 B aluop [2:0] $end
$var wire 4 C alucontrol [3:0] $end
$scope module ad $end
$var wire 6 D funct [5:0] $end
$var wire 3 E aluop [2:0] $end
$var reg 4 F alucontrol [3:0] $end
$upscope $end
$scope module md $end
$var wire 6 G op [5:0] $end
$var wire 1 4 regwrite $end
$var wire 1 5 regdst $end
$var wire 1 " memwrite $end
$var wire 1 8 memtoreg $end
$var wire 1 9 jump $end
$var wire 2 H immtype [1:0] $end
$var wire 1 A branch $end
$var wire 1 ; alusrc $end
$var wire 3 I aluop [2:0] $end
$var reg 12 J controls [11:0] $end
$upscope $end
$upscope $end
$scope module dp $end
$var wire 4 K alucontrol [3:0] $end
$var wire 1 ; alusrc $end
$var wire 1 $ clk $end
$var wire 2 L immtype [1:0] $end
$var wire 32 M instr [31:0] $end
$var wire 1 9 jump $end
$var wire 1 8 memtoreg $end
$var wire 1 6 pcsrc $end
$var wire 32 N readdata [31:0] $end
$var wire 1 5 regdst $end
$var wire 1 4 regwrite $end
$var wire 1 % reset $end
$var wire 1 2 zero $end
$var wire 5 O writereg [4:0] $end
$var wire 32 P writedata [31:0] $end
$var wire 32 Q srcb [31:0] $end
$var wire 32 R srca [31:0] $end
$var wire 32 S signimmsh [31:0] $end
$var wire 32 T result [31:0] $end
$var wire 32 U pcplus4 [31:0] $end
$var wire 32 V pcnextbr [31:0] $end
$var wire 32 W pcnext [31:0] $end
$var wire 32 X pcbranch [31:0] $end
$var wire 32 Y pc [31:0] $end
$var wire 32 Z immextv [31:0] $end
$var wire 32 [ aluout [31:0] $end
$scope module alu $end
$var wire 4 \ alucontrol [3:0] $end
$var wire 32 ] srcb [31:0] $end
$var wire 32 ^ srca [31:0] $end
$var reg 32 _ aluout [31:0] $end
$var reg 1 2 zero $end
$upscope $end
$scope module ie $end
$var wire 16 ` a [15:0] $end
$var wire 2 a immtype [1:0] $end
$var wire 32 b yzeroext [31:0] $end
$var wire 32 c ysignext [31:0] $end
$var wire 32 d ysethi [31:0] $end
$var wire 32 e y [31:0] $end
$scope module se $end
$var wire 16 f a [15:0] $end
$var wire 32 g y [31:0] $end
$upscope $end
$scope module sh $end
$var wire 16 h a [15:0] $end
$var wire 32 i y [31:0] $end
$upscope $end
$scope module ze $end
$var wire 16 j a [15:0] $end
$var wire 32 k y [31:0] $end
$upscope $end
$upscope $end
$scope module immsh $end
$var wire 32 l a [31:0] $end
$var wire 32 m y [31:0] $end
$upscope $end
$scope module pcadd1 $end
$var wire 32 n b [31:0] $end
$var wire 32 o y [31:0] $end
$var wire 32 p a [31:0] $end
$upscope $end
$scope module pcadd2 $end
$var wire 32 q a [31:0] $end
$var wire 32 r b [31:0] $end
$var wire 32 s y [31:0] $end
$upscope $end
$scope module pcbrmux $end
$var wire 32 t d0 [31:0] $end
$var wire 32 u d1 [31:0] $end
$var wire 1 6 s $end
$var wire 32 v y [31:0] $end
$upscope $end
$scope module pcmux $end
$var wire 32 w d0 [31:0] $end
$var wire 32 x d1 [31:0] $end
$var wire 1 9 s $end
$var wire 32 y y [31:0] $end
$upscope $end
$scope module pcreg $end
$var wire 1 $ clk $end
$var wire 32 z d [31:0] $end
$var wire 1 % reset $end
$var reg 32 { q [31:0] $end
$upscope $end
$scope module resmux $end
$var wire 32 | d0 [31:0] $end
$var wire 32 } d1 [31:0] $end
$var wire 1 8 s $end
$var wire 32 ~ y [31:0] $end
$upscope $end
$scope module rf $end
$var wire 1 $ clk $end
$var wire 5 !" ra1 [4:0] $end
$var wire 5 "" ra2 [4:0] $end
$var wire 32 #" wd3 [31:0] $end
$var wire 1 4 we3 $end
$var wire 5 $" wa3 [4:0] $end
$var wire 32 %" rd2 [31:0] $end
$var wire 32 &" rd1 [31:0] $end
$upscope $end
$scope module srcbmux $end
$var wire 32 '" d0 [31:0] $end
$var wire 32 (" d1 [31:0] $end
$var wire 1 ; s $end
$var wire 32 )" y [31:0] $end
$upscope $end
$scope module wrmux $end
$var wire 5 *" d0 [4:0] $end
$var wire 5 +" d1 [4:0] $end
$var wire 1 5 s $end
$var wire 5 ," y [4:0] $end
$upscope $end
$upscope $end
$upscope $end
$upscope $end
$upscope $end
$enddefinitions $end
#0
$dumpvars
b10 ,"
b0 +"
b10 *"
b101 )"
b101 ("
bx '"
b0 &"
bx %"
b10 $"
b101 #"
b10 ""
b0 !"
b101 ~
b100000000000110000000000001100 }
b101 |
b0 {
b100 z
b100 y
b10000000000000010100 x
b100 w
b100 v
b11000 u
b100 t
b11000 s
b10100 r
b100 q
b0 p
b100 o
b100 n
b10100 m
b101 l
b101 k
b101 j
b1010000000000000000 i
b101 h
b101 g
b101 f
b101 e
b1010000000000000000 d
b101 c
b101 b
b0 a
b101 `
b101 _
b0 ^
b101 ]
b10 \
b101 [
b101 Z
b0 Y
b11000 X
b100 W
b100 V
b100 U
b101 T
b10100 S
b0 R
b101 Q
bx P
b10 O
b100000000000110000000000001100 N
b100000000000100000000000000101 M
b0 L
b10 K
b100010000000 J
b0 I
b0 H
b1000 G
b10 F
b0 E
b101 D
b10 C
b0 B
0A
b0 @
b1000 ?
b101 >
b10 =
b101 <
1;
b0 :
09
08
b0 7
06
05
14
bx 3
02
b100000000000110000000000001100 1
b100000000000100000000000000101 0
b100000000000100000000000000101 /
b0 .
b101 -
bx ,
b100000000000110000000000001100 +
b101 *
b100000000000100000000000000101 )
b0 (
b100000000000110000000000001100 '
bx &
1%
1$
b101 #
0"
bx !
$end
#5000
0$
#10000
b101 !
b101 &
b101 ,
b101 3
b101 P
b101 %"
b101 '"
1$
#15000
0$
#20000
1$
#22000
0%
#25000
0$
#30000
b1100 T
b1100 ~
b1100 #"
b111000100010000000100101 '
b111000100010000000100101 +
b111000100010000000100101 1
b111000100010000000100101 N
b111000100010000000100101 }
b1100 #
b1100 *
b1100 -
b1100 <
b1100 [
b1100 _
b1100 |
b110000 S
b110000 m
b110000 r
b1100 Q
b1100 ]
b1100 )"
b1100 Z
b1100 e
b1100 l
b1100 ("
bx !
bx &
bx ,
bx 3
bx P
bx %"
bx '"
b11 O
b11 $"
b11 ,"
b1000 W
b1000 y
b1000 z
b1100 >
b1100 D
b11000000000000110000 x
b11 ""
b11 *"
b1100 c
b1100 g
b11000000000000000000 d
b11000000000000000000 i
b1100 b
b1100 k
b1100 `
b1100 f
b1100 h
b1100 j
b1000 V
b1000 v
b1000 w
b100000000000110000000000001100 )
b100000000000110000000000001100 /
b100000000000110000000000001100 0
b100000000000110000000000001100 M
b1 .
b111000 X
b111000 s
b111000 u
b1000 U
b1000 o
b1000 q
b1000 t
b100 (
b100 7
b100 Y
b100 p
b100 {
1$
#35000
0$
#40000
b11 T
b11 ~
b11 #"
b100000000000100000000000000101 '
b100000000000100000000000000101 +
b100000000000100000000000000101 1
b100000000000100000000000000101 N
b100000000000100000000000000101 }
02
b11 #
b11 *
b11 -
b11 <
b11 [
b11 _
b11 |
b11111111111111111111111111011100 S
b11111111111111111111111111011100 m
b11111111111111111111111111011100 r
b11111111111111111111111111110111 Q
b11111111111111111111111111110111 ]
b11111111111111111111111111110111 )"
b11111111111111111111111111110111 Z
b11111111111111111111111111110111 e
b11111111111111111111111111110111 l
b11111111111111111111111111110111 ("
b1100 R
b1100 ^
b1100 &"
b111 O
b111 $"
b111 ,"
b1100 W
b1100 y
b1100 z
b110111 >
b110111 D
b1100111111111111111011100 x
b11 !"
b111 ""
b111 *"
b11111 +"
b11111111111111111111111111110111 c
b11111111111111111111111111110111 g
b11111111111101110000000000000000 d
b11111111111101110000000000000000 i
b1111111111110111 b
b1111111111110111 k
b1111111111110111 `
b1111111111110111 f
b1111111111110111 h
b1111111111110111 j
bx !
bx &
bx ,
bx 3
bx P
bx %"
bx '"
b1100 V
b1100 v
b1100 w
b100000011001111111111111110111 )
b100000011001111111111111110111 /
b100000011001111111111111110111 0
b100000011001111111111111110111 M
b10 .
b11111111111111111111111111101000 X
b11111111111111111111111111101000 s
b11111111111111111111111111101000 u
b1100 U
b1100 o
b1100 q
b1100 t
b1000 (
b1000 7
b1000 Y
b1000 p
b1000 {
1$
#45000
0$
#50000
b1 =
b1 C
b1 F
b1 K
b1 \
b111 T
b111 ~
b111 #"
b100000000000110000000000001100 '
b100000000000110000000000001100 +
b100000000000110000000000001100 1
b100000000000110000000000001100 N
b100000000000110000000000001100 }
15
0;
b100 B
b100 E
b100 I
b111 #
b111 *
b111 -
b111 <
b111 [
b111 _
b111 |
b100100000100 J
b1000000010010100 S
b1000000010010100 m
b1000000010010100 r
b101 Q
b101 ]
b101 )"
b10000000100101 Z
b10000000100101 e
b10000000100101 l
b10000000100101 ("
b11 R
b11 ^
b11 &"
b100 O
b100 $"
b100 ,"
b10000 W
b10000 y
b10000 z
b0 ?
b0 G
b100101 >
b100101 D
b11100010001000000010010100 x
b111 !"
b10 ""
b10 *"
b100 +"
b10000000100101 c
b10000000100101 g
b100000001001010000000000000000 d
b100000001001010000000000000000 i
b10000000100101 b
b10000000100101 k
b10000000100101 `
b10000000100101 f
b10000000100101 h
b10000000100101 j
b101 !
b101 &
b101 ,
b101 3
b101 P
b101 %"
b101 '"
b10000 V
b10000 v
b10000 w
b111000100010000000100101 )
b111000100010000000100101 /
b111000100010000000100101 0
b111000100010000000100101 M
b11 .
b1000000010100100 X
b1000000010100100 s
b1000000010100100 u
b10000 U
b10000 o
b10000 q
b10000 t
b1100 (
b1100 7
b1100 Y
b1100 p
b1100 {
1$
#55000
0$
#60000
b100 T
b100 ~
b100 #"
b100000000000110000000000001100 '
b100000000000110000000000001100 +
b100000000000110000000000001100 1
b100000000000110000000000001100 N
b100000000000110000000000001100 }
b100 #
b100 *
b100 -
b100 <
b100 [
b100 _
b100 |
b0 =
b0 C
b0 F
b0 K
b0 \
b1010000010010000 S
b1010000010010000 m
b1010000010010000 r
b111 Q
b111 ]
b111 )"
b10100000100100 Z
b10100000100100 e
b10100000100100 l
b10100000100100 ("
b1100 R
b1100 ^
b1100 &"
b111 !
b111 &
b111 ,
b111 3
b111 P
b111 %"
b111 '"
b101 O
b101 $"
b101 ,"
b10100 W
b10100 y
b10100 z
b100100 >
b100100 D
b1100100001010000010010000 x
b11 !"
b100 ""
b100 *"
b101 +"
b10100000100100 c
b10100000100100 g
b101000001001000000000000000000 d
b101000001001000000000000000000 i
b10100000100100 b
b10100000100100 k
b10100000100100 `
b10100000100100 f
b10100000100100 h
b10100000100100 j
b10100 V
b10100 v
b10100 w
b11001000010100000100100 )
b11001000010100000100100 /
b11001000010100000100100 0
b11001000010100000100100 M
b100 .
b1010000010100100 X
b1010000010100100 s
b1010000010100100 u
b10100 U
b10100 o
b10100 q
b10100 t
b10000 (
b10000 7
b10000 Y
b10000 p
b10000 {
1$
#65000
0$
#70000
b1011 T
b1011 ~
b1011 #"
b100000011001111111111111110111 '
b100000011001111111111111110111 +
b100000011001111111111111110111 1
b100000011001111111111111110111 N
b100000011001111111111111110111 }
b1011 #
b1011 *
b1011 -
b1011 <
b1011 [
b1011 _
b1011 |
b10 =
b10 C
b10 F
b10 K
b10 \
b1010000010000000 S
b1010000010000000 m
b1010000010000000 r
b10100000100000 Z
b10100000100000 e
b10100000100000 l
b10100000100000 ("
b100 R
b100 ^
b100 &"
b11000 W
b11000 y
b11000 z
b100000 >
b100000 D
b10100100001010000010000000 x
b101 !"
b10100000100000 c
b10100000100000 g
b101000001000000000000000000000 d
b101000001000000000000000000000 i
b10100000100000 b
b10100000100000 k
b10100000100000 `
b10100000100000 f
b10100000100000 h
b10100000100000 j
b11000 V
b11000 v
b11000 w
b101001000010100000100000 )
b101001000010100000100000 /
b101001000010100000100000 0
b101001000010100000100000 M
b101 .
b1010000010011000 X
b1010000010011000 s
b1010000010011000 u
b11000 U
b11000 o
b11000 q
b11000 t
b10100 (
b10100 7
b10100 Y
b10100 p
b10100 {
1$
#75000
0$
#80000
04
05
1A
b1 B
b1 E
b1 I
b1000 T
b1000 ~
b1000 #"
b100000011001111111111111110111 '
b100000011001111111111111110111 +
b100000011001111111111111110111 1
b100000011001111111111111110111 N
b100000011001111111111111110111 }
b1000001 J
b110 =
b110 C
b110 F
b110 K
b110 \
b1000 #
b1000 *
b1000 -
b1000 <
b1000 [
b1000 _
b1000 |
b101100 S
b101100 m
b101100 r
b11 Q
b11 ]
b11 )"
b1011 Z
b1011 e
b1011 l
b1011 ("
b11 !
b11 &
b11 ,
b11 3
b11 P
b11 %"
b11 '"
b111 O
b111 $"
b111 ,"
b11100 W
b11100 y
b11100 z
b100 ?
b100 G
b1011 >
b1011 D
b10100111000000000000101100 x
b111 ""
b111 *"
b0 +"
b1011 c
b1011 g
b10110000000000000000 d
b10110000000000000000 i
b1011 b
b1011 k
b1011 `
b1011 f
b1011 h
b1011 j
b1011 R
b1011 ^
b1011 &"
b11100 V
b11100 v
b11100 w
b10000101001110000000000001011 )
b10000101001110000000000001011 /
b10000101001110000000000001011 0
b10000101001110000000000001011 M
b110 .
b1001000 X
b1001000 s
b1001000 u
b11100 U
b11100 o
b11100 q
b11100 t
b11000 (
b11000 7
b11000 Y
b11000 p
b11000 {
1$
#85000
0$
#90000
b111 =
b111 C
b111 F
b111 K
b111 \
b0 T
b0 ~
b0 #"
b100000000000100000000000000101 '
b100000000000100000000000000101 +
b100000000000100000000000000101 1
b100000000000100000000000000101 N
b100000000000100000000000000101 }
14
15
0A
b100 B
b100 E
b100 I
b0 #
b0 *
b0 -
b0 <
b0 [
b0 _
b0 |
b100100000100 J
b1000000010101000 S
b1000000010101000 m
b1000000010101000 r
b111 Q
b111 ]
b111 )"
b10000000101010 Z
b10000000101010 e
b10000000101010 l
b10000000101010 ("
b1100 R
b1100 ^
b1100 &"
b111 !
b111 &
b111 ,
b111 3
b111 P
b111 %"
b111 '"
b100 O
b100 $"
b100 ,"
b100000 W
b100000 y
b100000 z
b0 ?
b0 G
b101010 >
b101010 D
b1100100001000000010101000 x
b11 !"
b100 ""
b100 *"
b100 +"
b10000000101010 c
b10000000101010 g
b100000001010100000000000000000 d
b100000001010100000000000000000 i
b10000000101010 b
b10000000101010 k
b10000000101010 `
b10000000101010 f
b10000000101010 h
b10000000101010 j
b100000 V
b100000 v
b100000 w
b11001000010000000101010 )
b11001000010000000101010 /
b11001000010000000101010 0
b11001000010000000101010 M
b111 .
b1000000011001000 X
b1000000011001000 s
b1000000011001000 u
b100000 U
b100000 o
b100000 q
b100000 t
b11100 (
b11100 7
b11100 Y
b11100 p
b11100 {
1$
#95000
0$
#100000
16
04
05
1A
b1 B
b1 E
b1 I
12
b1000001 J
b110 =
b110 C
b110 F
b110 K
b110 \
b100 S
b100 m
b100 r
b1 Z
b1 e
b1 l
b1 ("
b0 R
b0 ^
b0 &"
b0 O
b0 $"
b0 ,"
b0 Q
b0 ]
b0 )"
b101000 W
b101000 y
b101000 z
b100 ?
b100 G
b1 >
b1 D
b10000000000000000000000100 x
b100 !"
b0 ""
b0 *"
b0 +"
b1 c
b1 g
b10000000000000000 d
b10000000000000000 i
b1 b
b1 k
b1 `
b1 f
b1 h
b1 j
b0 !
b0 &
b0 ,
b0 3
b0 P
b0 %"
b0 '"
b101000 V
b101000 v
b101000 w
b10000100000000000000000000001 )
b10000100000000000000000000001 /
b10000100000000000000000000001 0
b10000100000000000000000000001 M
b1000 .
b101000 X
b101000 s
b101000 u
b100100 U
b100100 o
b100100 q
b100100 t
b100000 (
b100000 7
b100000 Y
b100000 p
b100000 {
1$
#105000
0$
#110000
b111 =
b111 C
b111 F
b111 K
b111 \
06
b1 T
b1 ~
b1 #"
b100000000000100000000000000101 '
b100000000000100000000000000101 +
b100000000000100000000000000101 1
b100000000000100000000000000101 N
b100000000000100000000000000101 }
14
15
0A
b100 B
b100 E
b100 I
02
b1 #
b1 *
b1 -
b1 <
b1 [
b1 _
b1 |
b100100000100 J
b1000000010101000 S
b1000000010101000 m
b1000000010101000 r
b101 Q
b101 ]
b101 )"
b10000000101010 Z
b10000000101010 e
b10000000101010 l
b10000000101010 ("
b11 R
b11 ^
b11 &"
b101 !
b101 &
b101 ,
b101 3
b101 P
b101 %"
b101 '"
b100 O
b100 $"
b100 ,"
b101100 W
b101100 y
b101100 z
b0 ?
b0 G
b101010 >
b101010 D
b11100010001000000010101000 x
b111 !"
b10 ""
b10 *"
b100 +"
b10000000101010 c
b10000000101010 g
b100000001010100000000000000000 d
b100000001010100000000000000000 i
b10000000101010 b
b10000000101010 k
b10000000101010 `
b10000000101010 f
b10000000101010 h
b10000000101010 j
b101100 V
b101100 v
b101100 w
b111000100010000000101010 )
b111000100010000000101010 /
b111000100010000000101010 0
b111000100010000000101010 M
b1010 .
b1000000011010100 X
b1000000011010100 s
b1000000011010100 u
b101100 U
b101100 o
b101100 q
b101100 t
b101000 (
b101000 7
b101000 Y
b101000 p
b101000 {
1$
#115000
0$
#120000
b1100 T
b1100 ~
b1100 #"
b111000100010000000100101 '
b111000100010000000100101 +
b111000100010000000100101 1
b111000100010000000100101 N
b111000100010000000100101 }
b1100 #
b1100 *
b1100 -
b1100 <
b1100 [
b1100 _
b1100 |
b10 =
b10 C
b10 F
b10 K
b10 \
b1110000010000000 S
b1110000010000000 m
b1110000010000000 r
b1011 Q
b1011 ]
b1011 )"
b11100000100000 Z
b11100000100000 e
b11100000100000 l
b11100000100000 ("
b1 R
b1 ^
b1 &"
b1011 !
b1011 &
b1011 ,
b1011 3
b1011 P
b1011 %"
b1011 '"
b111 O
b111 $"
b111 ,"
b110000 W
b110000 y
b110000 z
b100000 >
b100000 D
b10000101001110000010000000 x
b100 !"
b101 ""
b101 *"
b111 +"
b11100000100000 c
b11100000100000 g
b111000001000000000000000000000 d
b111000001000000000000000000000 i
b11100000100000 b
b11100000100000 k
b11100000100000 `
b11100000100000 f
b11100000100000 h
b11100000100000 j
b110000 V
b110000 v
b110000 w
b100001010011100000100000 )
b100001010011100000100000 /
b100001010011100000100000 0
b100001010011100000100000 M
b1011 .
b1110000010110000 X
b1110000010110000 s
b1110000010110000 u
b110000 U
b110000 o
b110000 q
b110000 t
b101100 (
b101100 7
b101100 Y
b101100 p
b101100 {
1$
#125000
0$
