practice5/tmips1_2/top.v
/*
 * From D. M. Harris and S. L. Harris, "Digital Design and Computer Architecture"
 */
`timescale 1ns / 1ps
 // rename for your .dat-file
`define DATFILE "sample1.dat"

module dmem(
    input  clk, we,
    input  [31:0] a, wd,
    output [31:0] rd);

   reg [31:0] RAM[63:0];
   assign rd = RAM[a[31:2]];
	
   always @ (posedge clk)
     if (we)
       RAM[a[31:2]] <= wd;

   initial
     begin
	$readmemh (`DATFILE, RAM);
     end

endmodule

module imem (
    input  [5:0]  a,
    output [31:0] rd);
				
   reg [31:0]  RAM[63:0];
	
   initial
     begin
	$readmemh (`DATFILE, RAM);
     end
		
   assign rd = RAM[a];
endmodule

module top(
    input clk,
    input reset,
    output [31:0] writedata,
    output [31:0] dataaddr,
    output memwrite
    );

   wire [31:0] pc, instr, readdata;
   // instantiate a processor and memories
   mips mips (clk, reset, pc, instr, memwrite, dataaddr, writedata, readdata);
   imem imem (pc[7:2], instr);
   dmem dmem (clk, memwrite, dataaddr, writedata, readdata);
	
endmodule

practice5/tmips1_2/alu.v
/*
 * From D. M. Harris and S. L. Harris, "Digital Design and Computer Architecture"
 */
`timescale 1ns / 1ps
module alu(
    input [31:0] srca,
    input [31:0] srcb,
    input [3:0] alucontrol,
    output reg [31:0] aluout,
    output reg zero
    );

   always @ (*)
     begin
			case (alucontrol)
			  4'b0000: aluout <= srca & srcb;
			  4'b0001: aluout <= srca | srcb;
			  4'b0010: aluout <= srca + srcb;
			  4'b0110: aluout <= srca - srcb;
			  4'b0111: aluout <= (srca-srcb)>>31;
			endcase
			zero <= (srca == srcb) ? 1 : 0;
     end
	
endmodule




module alutest;

   reg [31:0] opa, opb;
   reg [3:0]  aluc;
   wire [31:0] res;
   wire        zero;
   
   alu alu1(opa, opb, aluc, res, zero);

   initial begin
      $dumpfile("alutest.vcd");
      $dumpvars(0, alutest);
      aluc = 2; #1
      opa = 3; opb = 1;   #1
      aluc = 6; opa = 4; opb = -2; #2
      $finish;
   end
   

endmodule // alutest

tmips/datapath.v
/*
 * From D. M. Harris and S. L. Harris, "Digital Design and Computer Architecture"
 */
`timescale 1ns / 1ps
module adder(
    input  [31:0] a, b,
    output [31:0] y);

   assign y = a + b;
endmodule

module sl2 (
    input  [31:0] a,
    output [31:0] y);
				
   assign y = {a[29:00], 2'b00};
endmodule

module signext (
    input  [15:0] a,
    output [31:0] y);
					
   assign y = {{16{a[15]}}, a};
endmodule

module zeroext (
    input  [15:0] a,
    output [31:0] y);
					
   assign y = {16'b0, a};
endmodule

module sethi (
    input  [15:0] a,
    output [31:0] y);
					
   assign y = {a, 16'b0};
endmodule

// immtype:
//  - 00 signext
//  - 01 zeroext
//  - 10 sethi
module immext (
    input  [1:0] immtype,
    input  [15:0] a,
    output [31:0] y);

   wire [31:0] ysignext;
   wire [31:0] yzeroext;
   wire [31:0] ysethi;

   signext  se(a, ysignext);
   zeroext  ze(a, yzeroext);
   sethi    sh(a, ysethi);

   assign y = immtype[1] ? ysethi
	      : (immtype[0] ? yzeroext : ysignext);
   
endmodule

module flopr # (parameter WIDTH = 8)
   (input	clk, reset,
    input	[WIDTH-1:0] d,
    output reg [WIDTH-1:0]  q);
					
   always @ (posedge clk, posedge reset)
     if (reset) q <= 0;
     else	q <= d;
endmodule

module mux2 # (parameter WIDTH = 8)
   (input  [WIDTH-1:0] d0, d1,
    input  s,
    output [WIDTH-1:0] y);
				
   assign y = s ? d1 : d0;
endmodule

module regfile(
    input clk,
    input we3,
    input [4:0] ra1,
    input [4:0] ra2,
    input [4:0] wa3,
    input [31:0] wd3,
    output [31:0] rd1,
    output [31:0] rd2
    );

   reg [31:0] 	  rf[31:0];
	
   // 3-port register file
   always @ (posedge clk)
     if (we3) rf[wa3] <= wd3;
		
   assign rd1 = (ra1 != 0) ? rf[ra1] : 0;
   assign rd2 = (ra2 != 0) ? rf[ra2] : 0;
endmodule

module datapath(
    input  clk,
    input  reset,
    input  memtoreg,
    input  pcsrc,
    input  alusrc,
    input  regdst,
    input  [1:0] immtype,
    input  regwrite,
    input  jump,
    input  [3:0] alucontrol,
    output zero,
    output [31:0] pc,
    input  [31:0] instr,
    output [31:0] aluout,
    output [31:0] writedata,
    input  [31:0] readdata
    );

   wire [4:0] 	 writereg;
   wire [31:0] 	 pcnext, pcnextbr, pcplus4, pcbranch;
   wire [31:0] 	 immextv, signimmsh;
   wire [31:0] 	 srca, srcb;
   wire [31:0] 	 result;
	
   // for next PC
   flopr #(32)	pcreg(clk, reset, pcnext, pc);
   adder	pcadd1 (pc, 32'b100, pcplus4);
   sl2		immsh(immextv, signimmsh);
   adder	pcadd2(pcplus4, signimmsh, pcbranch);
   mux2 #(32)   pcbrmux(pcplus4, pcbranch, pcsrc, pcnextbr);
   mux2 #(32)   pcmux(pcnextbr, {pcplus4[31:28], instr[25:0], 2'b00},
		      jump, pcnext);
							
   // reg-file logic
   regfile	rf(clk, regwrite, instr[25:21], instr[20:16], writereg,
		   result, srca, writedata);
   mux2 #(5)	wrmux(instr[20:16], instr[15:11], regdst, writereg);
   mux2 #(32)	resmux(aluout, readdata, memtoreg, result);
   immext	ie(immtype, instr[15:0], immextv);
	
   // ALU logic
   mux2 #(32) srcbmux(writedata, immextv, alusrc, srcb);
   alu alu(srca, srcb, alucontrol, aluout, zero);
endmodule

tmips/controller.v
/*
 * From D. M. Harris and S. L. Harris, "Digital Design and Computer Architecture"
 */
`timescale 1ns / 1ps
module maindec(
    input [5:0] op,
    output memtoreg,
    output memwrite,
    output branch,
    output alusrc,
    output regdst,
    output [1:0] immtype,
    output regwrite,
    output jump,
    output [2:0] aluop
    );

   reg [11:0] 	 controls;
	
   assign { regwrite, immtype, regdst, alusrc, branch, memwrite,
	    memtoreg, jump, aluop } = controls;
				
   always @ (*)
     case (op)
       6'b000000: controls <= 12'b100100000100; //Rtype
       6'b100011: controls <= 12'b100010010000; //LW
       6'b101011: controls <= 12'b000010100000; //SW
       6'b000100: controls <= 12'b000001000001; //BEQ
       6'b001000: controls <= 12'b100010000000; //ADDI
       6'b001111: controls <= 12'b110010000011; //LUI
       6'b001101: controls <= 12'b101010000011; //ORI
       6'b001100: controls <= 12'b101010000010; //ANDI
       6'b000010: controls <= 12'b000000001000; //J
       default:   controls <= 12'bxxxxxxxxxxxx; //???
     endcase

endmodule

module aludec(
    input [5:0] funct,
    input [2:0] aluop,
    output reg [3:0] alucontrol
    );

   always @ (*)
     case (aluop)
        3'b000: alucontrol <= 4'b0010; // addition
        3'b001: alucontrol <= 4'b0110; // subtraction
        3'b011: alucontrol <= 4'b0001; // or
        3'b010: alucontrol <= 4'b0000; // ADD
        default: case (funct) // Rtype (aluop is 100)
          6'b100000: alucontrol <= 4'b0010; //ADD
          6'b100010: alucontrol <= 4'b0110; //SUB
          6'b100100: alucontrol <= 4'b0000; //AND
          6'b100101: alucontrol <= 4'b0001; //OR
          6'b100111: alucontrol <= 4'b1100; //NOR
          6'b101010: alucontrol <= 4'b0111; //SLT
          default:   alucontrol <= 4'bxxxx; //???
        endcase
     endcase
endmodule

module controller(
    input [5:0] op,
    input [5:0] funct,
    input zero,
    output memtoreg,
    output memwrite,
    output pcsrc,
    output alusrc,
    output regdst,
    output [1:0] immtype,
    output regwrite,
    output jump,
    output [3:0] alucontrol
    );

   wire [2:0] 	 aluop;
   wire 	 branch;

   maindec md (op, memtoreg, memwrite, branch, alusrc,
	       regdst, immtype, regwrite, jump, aluop);
   aludec ad (funct, aluop, alucontrol);

   assign pcsrc = branch & zero;
endmodule

module testcont;
   reg [5:0] op;
   reg [5:0] funct;
   reg 	     zero;
   wire      memtoreg, memwrite, pcsrc, alusrc, regdst, regwrite, jump;
   wire [1:0] immtype;
   wire [3:0] alucontrol;

   controller ctl(op, funct, zero, memtoreg, memwrite, pcsrc,
		  alusrc, regdst, immtype, regwrite, jump, alucontrol);

   initial begin
      $dumpfile("testcont.vcd");
      $dumpvars(0, testcont);
      zero = 0; op = 0; funct = 6'b100101; #1
      op = 'h2b; #1 // 101011
      op = 'h04; #1 // 000100
      op = 'h08; #1 // 001000
      op = 'h02; #1 // 000010
      op = 0; funct = 'h27; #1 // funct=100111, NOR
      op = 'h0c; #1 // 001100, ANDI
      $finish;
   end
endmodule // testcont

practice5/tmips1_1/mips.v
/*
 * From D. M. Harris and S. L. Harris, "Digital Design and Computer Architecture"
 */
`timescale 1ns / 1ps
module mips(
    input  clk,
    input  reset,
    output [31:0] pc,
    input  [31:0] instr,
    output memwrite,
    output [31:0] aluout,
    output [31:0] writedata,
    input  [31:0] readdata
    );

   wire 	  memtoreg, branch, alusrc, regdst, regwrite, jump, zero;
   wire [1:0] 	  immtype;
 	  
   wire [3:0] 	  alucontrol;
	
   controller ctl(instr[31:26], instr[5:0], zero, memtoreg, memwrite, pcsrc,
		  alusrc, regdst, immtype, regwrite, jump, alucontrol);
   datapath dp(clk, reset, memtoreg, pcsrc, alusrc, regdst, immtype, regwrite,
	       jump, alucontrol, zero, pc, instr, aluout, writedata, readdata);
					
endmodule

practice5/tmips1_2/testbench.v
/*
 * From D. M. Harris and S. L. Harris, "Digital Design and Computer Architecture"
 */
`timescale 1ns / 1ps
module testbench();

   reg	clk;
   reg	reset;
	
   wire [31:0] writedata, dataaddr;
   wire        memwrite;
	
   // instantiate device to be tested
   top dut (clk, reset, writedata, dataaddr, memwrite);
	
   // initialize test
   initial begin
      $dumpfile("testb.vcd");
      $dumpvars(0, testbench);
      reset <= 1; # 22; reset <= 0;
   end
		
   // generate clock to sequence tests
   always
     begin
	clk <= 1; #5; clk <= 0; #5;
     end
		
   // check results
   always @ (negedge clk)
     begin
	if (memwrite) begin
	   if (dataaddr === 84 & writedata === 1048857) begin
	      $display ("Simulation succeeded");
	      $finish;
	   end else if (dataaddr === 84) begin
	      $display ("Simulation failed");
	      $finish;
	   end
	end
     end

endmodule

practice5/tmips1_2/testb.vcd
$date
	Mon Dec 16 13:54:50 2019
$end
$version
	Icarus Verilog
$end
$timescale
	1ps
$end
$scope module testbench $end
$var wire 32 ! writedata [31:0] $end
$var wire 1 " memwrite $end
$var wire 32 # dataaddr [31:0] $end
$var reg 1 $ clk $end
$var reg 1 % reset $end
$scope module dut $end
$var wire 1 $ clk $end
$var wire 1 % reset $end
$var wire 32 & writedata [31:0] $end
$var wire 32 ' readdata [31:0] $end
$var wire 32 ( pc [31:0] $end
$var wire 1 " memwrite $end
$var wire 32 ) instr [31:0] $end
$var wire 32 * dataaddr [31:0] $end
$scope module dmem $end
$var wire 1 $ clk $end
$var wire 32 + rd [31:0] $end
$var wire 1 " we $end
$var wire 32 , wd [31:0] $end
$var wire 32 - a [31:0] $end
$upscope $end
$scope module imem $end
$var wire 6 . a [5:0] $end
$var wire 32 / rd [31:0] $end
$upscope $end
$scope module mips $end
$var wire 1 $ clk $end
$var wire 32 0 instr [31:0] $end
$var wire 32 1 readdata [31:0] $end
$var wire 1 % reset $end
$var wire 1 2 zero $end
$var wire 32 3 writedata [31:0] $end
$var wire 1 4 regwrite $end
$var wire 1 5 regdst $end
$var wire 1 6 pcsrc $end
$var wire 32 7 pc [31:0] $end
$var wire 1 " memwrite $end
$var wire 1 8 memtoreg $end
$var wire 1 9 jump $end
$var wire 2 : immtype [1:0] $end
$var wire 1 ; alusrc $end
$var wire 32 < aluout [31:0] $end
$var wire 4 = alucontrol [3:0] $end
$scope module ctl $end
$var wire 6 > funct [5:0] $end
$var wire 6 ? op [5:0] $end
$var wire 1 6 pcsrc $end
$var wire 1 2 zero $end
$var wire 1 4 regwrite $end
$var wire 1 5 regdst $end
$var wire 1 " memwrite $end
$var wire 1 8 memtoreg $end
$var wire 1 9 jump $end
$var wire 2 @ immtype [1:0] $end
$var wire 1 A branch $end
$var wire 1 ; alusrc $end
$var wire 3 B aluop [2:0] $end
$var wire 4 C alucontrol [3:0] $end
$scope module ad $end
$var wire 6 D funct [5:0] $end
$var wire 3 E aluop [2:0] $end
$var reg 4 F alucontrol [3:0] $end
$upscope $end
$scope module md $end
$var wire 6 G op [5:0] $end
$var wire 1 4 regwrite $end
$var wire 1 5 regdst $end
$var wire 1 " memwrite $end
$var wire 1 8 memtoreg $end
$var wire 1 9 jump $end
$var wire 2 H immtype [1:0] $end
$var wire 1 A branch $end
$var wire 1 ; alusrc $end
$var wire 3 I aluop [2:0] $end
$var reg 12 J controls [11:0] $end
$upscope $end
$upscope $end
$scope module dp $end
$var wire 4 K alucontrol [3:0] $end
$var wire 1 ; alusrc $end
$var wire 1 $ clk $end
$var wire 2 L immtype [1:0] $end
$var wire 32 M instr [31:0] $end
$var wire 1 9 jump $end
$var wire 1 8 memtoreg $end
$var wire 1 6 pcsrc $end
$var wire 32 N readdata [31:0] $end
$var wire 1 5 regdst $end
$var wire 1 4 regwrite $end
$var wire 1 % reset $end
$var wire 1 2 zero $end
$var wire 5 O writereg [4:0] $end
$var wire 32 P writedata [31:0] $end
$var wire 32 Q srcb [31:0] $end
$var wire 32 R srca [31:0] $end
$var wire 32 S signimmsh [31:0] $end
$var wire 32 T result [31:0] $end
$var wire 32 U pcplus4 [31:0] $end
$var wire 32 V pcnextbr [31:0] $end
$var wire 32 W pcnext [31:0] $end
$var wire 32 X pcbranch [31:0] $end
$var wire 32 Y pc [31:0] $end
$var wire 32 Z immextv [31:0] $end
$var wire 32 [ aluout [31:0] $end
$scope module alu $end
$var wire 4 \ alucontrol [3:0] $end
$var wire 32 ] srcb [31:0] $end
$var wire 32 ^ srca [31:0] $end
$var reg 32 _ aluout [31:0] $end
$var reg 1 2 zero $end
$upscope $end
$scope module ie $end
$var wire 16 ` a [15:0] $end
$var wire 2 a immtype [1:0] $end
$var wire 32 b yzeroext [31:0] $end
$var wire 32 c ysignext [31:0] $end
$var wire 32 d ysethi [31:0] $end
$var wire 32 e y [31:0] $end
$scope module se $end
$var wire 16 f a [15:0] $end
$var wire 32 g y [31:0] $end
$upscope $end
$scope module sh $end
$var wire 16 h a [15:0] $end
$var wire 32 i y [31:0] $end
$upscope $end
$scope module ze $end
$var wire 16 j a [15:0] $end
$var wire 32 k y [31:0] $end
$upscope $end
$upscope $end
$scope module immsh $end
$var wire 32 l a [31:0] $end
$var wire 32 m y [31:0] $end
$upscope $end
$scope module pcadd1 $end
$var wire 32 n b [31:0] $end
$var wire 32 o y [31:0] $end
$var wire 32 p a [31:0] $end
$upscope $end
$scope module pcadd2 $end
$var wire 32 q a [31:0] $end
$var wire 32 r b [31:0] $end
$var wire 32 s y [31:0] $end
$upscope $end
$scope module pcbrmux $end
$var wire 32 t d0 [31:0] $end
$var wire 32 u d1 [31:0] $end
$var wire 1 6 s $end
$var wire 32 v y [31:0] $end
$upscope $end
$scope module pcmux $end
$var wire 32 w d0 [31:0] $end
$var wire 32 x d1 [31:0] $end
$var wire 1 9 s $end
$var wire 32 y y [31:0] $end
$upscope $end
$scope module pcreg $end
$var wire 1 $ clk $end
$var wire 32 z d [31:0] $end
$var wire 1 % reset $end
$var reg 32 { q [31:0] $end
$upscope $end
$scope module resmux $end
$var wire 32 | d0 [31:0] $end
$var wire 32 } d1 [31:0] $end
$var wire 1 8 s $end
$var wire 32 ~ y [31:0] $end
$upscope $end
$scope module rf $end
$var wire 1 $ clk $end
$var wire 5 !" ra1 [4:0] $end
$var wire 5 "" ra2 [4:0] $end
$var wire 32 #" wd3 [31:0] $end
$var wire 1 4 we3 $end
$var wire 5 $" wa3 [4:0] $end
$var wire 32 %" rd2 [31:0] $end
$var wire 32 &" rd1 [31:0] $end
$upscope $end
$scope module srcbmux $end
$var wire 32 '" d0 [31:0] $end
$var wire 32 (" d1 [31:0] $end
$var wire 1 ; s $end
$var wire 32 )" y [31:0] $end
$upscope $end
$scope module wrmux $end
$var wire 5 *" d0 [4:0] $end
$var wire 5 +" d1 [4:0] $end
$var wire 1 5 s $end
$var wire 5 ," y [4:0] $end
$upscope $end
$upscope $end
$upscope $end
$upscope $end
$upscope $end
$enddefinitions $end
#0
$dumpvars
b1 ,"
b0 +"
b1 *"
b100000000000000000000 )"
b100000000000000000000 ("
bx '"
b0 &"
bx %"
b1 $"
b100000000000000000000 #"
b1 ""
b0 !"
b100000000000000000000 ~
bx }
b100000000000000000000 |
b0 {
b100 z
b100 y
b1000000000001000000 x
b100 w
b100 v
b10000000000000000000100 u
b100 t
b10000000000000000000100 s
b10000000000000000000000 r
b100 q
b0 p
b100 o
b100 n
b10000000000000000000000 m
b100000000000000000000 l
b10000 k
b10000 j
b100000000000000000000 i
b10000 h
b10000 g
b10000 f
b100000000000000000000 e
b100000000000000000000 d
b10000 c
b10000 b
b10 a
b10000 `
b100000000000000000000 _
b0 ^
b100000000000000000000 ]
b1 \
b100000000000000000000 [
b100000000000000000000 Z
b0 Y
b10000000000000000000100 X
b100 W
b100 V
b100 U
b100000000000000000000 T
b10000000000000000000000 S
b0 R
b100000000000000000000 Q
bx P
b1 O
bx N
b111100000000010000000000010000 M
b10 L
b1 K
b110010000011 J
b11 I
b10 H
b1111 G
b1 F
b11 E
b10000 D
b1 C
b11 B
0A
b10 @
b1111 ?
b10000 >
b1 =
b100000000000000000000 <
1;
b10 :
09
08
b0 7
06
05
14
bx 3
02
bx 1
b111100000000010000000000010000 0
b111100000000010000000000010000 /
b0 .
b100000000000000000000 -
bx ,
bx +
b100000000000000000000 *
b111100000000010000000000010000 )
b0 (
bx '
bx &
1%
1$
b100000000000000000000 #
0"
bx !
$end
#5000
0$
#10000
b100000000000000000000 !
b100000000000000000000 &
b100000000000000000000 ,
b100000000000000000000 3
b100000000000000000000 P
b100000000000000000000 %"
b100000000000000000000 '"
1$
#15000
0$
#20000
1$
#22000
0%
#25000
0$
#30000
b111100000000010000000000010000 '
b111100000000010000000000010000 +
b111100000000010000000000010000 1
b111100000000010000000000010000 N
b111100000000010000000000010000 }
b10 =
b10 C
b10 F
b10 K
b10 \
b1 T
b1 ~
b1 #"
b0 :
b0 @
b0 H
b0 L
b0 a
b0 B
b0 E
b0 I
b1 #
b1 *
b1 -
b1 <
b1 [
b1 _
b1 |
b100010000000 J
b100 S
b100 m
b100 r
b1 Q
b1 ]
b1 )"
bx !
bx &
bx ,
bx 3
bx P
bx %"
bx '"
b10 O
b10 $"
b10 ,"
b1 Z
b1 e
b1 l
b1 ("
b1000 W
b1000 y
b1000 z
b1000 ?
b1000 G
b1 >
b1 D
b10000000000000000100 x
b10 ""
b10 *"
b1 c
b1 g
b10000000000000000 d
b10000000000000000 i
b1 b
b1 k
b1 `
b1 f
b1 h
b1 j
b1000 V
b1000 v
b1000 w
b100000000000100000000000000001 )
b100000000000100000000000000001 /
b100000000000100000000000000001 0
b100000000000100000000000000001 M
b1 .
b1100 X
b1100 s
b1100 u
b1000 U
b1000 o
b1000 q
b1000 t
b100 (
b100 7
b100 Y
b100 p
b100 {
1$
#35000
0$
#40000
b1011 T
b1011 ~
b1011 #"
b100000000000110000000000001011 '
b100000000000110000000000001011 +
b100000000000110000000000001011 1
b100000000000110000000000001011 N
b100000000000110000000000001011 }
b1011 #
b1011 *
b1011 -
b1011 <
b1011 [
b1011 _
b1011 |
b101100 S
b101100 m
b101100 r
b1011 Q
b1011 ]
b1011 )"
b1011 Z
b1011 e
b1011 l
b1011 ("
b11 O
b11 $"
b11 ,"
b1100 W
b1100 y
b1100 z
b1011 >
b1011 D
b11000000000000101100 x
b11 ""
b11 *"
b1011 c
b1011 g
b10110000000000000000 d
b10110000000000000000 i
b1011 b
b1011 k
b1011 `
b1011 f
b1011 h
b1011 j
bx !
bx &
bx ,
bx 3
bx P
bx %"
bx '"
b1100 V
b1100 v
b1100 w
b100000000000110000000000001011 )
b100000000000110000000000001011 /
b100000000000110000000000001011 0
b100000000000110000000000001011 M
b10 .
b111000 X
b111000 s
b111000 u
b1100 U
b1100 o
b1100 q
b1100 t
b1000 (
b1000 7
b1000 Y
b1000 p
b1000 {
1$
#45000
0$
#50000
b1 T
b1 ~
b1 #"
b111100000000010000000000010000 '
b111100000000010000000000010000 +
b111100000000010000000000010000 1
b111100000000010000000000010000 N
b111100000000010000000000010000 }
b1 #
b1 *
b1 -
b1 <
b1 [
b1 _
b1 |
b100 S
b100 m
b100 r
b1 Q
b1 ]
b1 )"
b1 Z
b1 e
b1 l
b1 ("
b100 O
b100 $"
b100 ,"
b10000 W
b10000 y
b10000 z
b1 >
b1 D
b100000000000000000100 x
b100 ""
b100 *"
b1 c
b1 g
b10000000000000000 d
b10000000000000000 i
b1 b
b1 k
b1 `
b1 f
b1 h
b1 j
bx !
bx &
bx ,
bx 3
bx P
bx %"
bx '"
b10000 V
b10000 v
b10000 w
b100000000001000000000000000001 )
b100000000001000000000000000001 /
b100000000001000000000000000001 0
b100000000001000000000000000001 M
b11 .
b10100 X
b10100 s
b10100 u
b10000 U
b10000 o
b10000 q
b10000 t
b1100 (
b1100 7
b1100 Y
b1100 p
b1100 {
1$
#55000
0$
#60000
b0 =
b0 C
b0 F
b0 K
b0 \
b1 T
b1 ~
b1 #"
b1 :
b1 @
b1 H
b1 L
b1 a
b10 B
b10 E
b10 I
12
b1 #
b1 *
b1 -
b1 <
b1 [
b1 _
b1 |
b101010000010 J
b1 R
b1 ^
b1 &"
b101 O
b101 $"
b101 ,"
b10100 W
b10100 y
b10100 z
b1100 ?
b1100 G
b1000101000000000000000100 x
b10 !"
b101 ""
b101 *"
bx !
bx &
bx ,
bx 3
bx P
bx %"
bx '"
b10100 V
b10100 v
b10100 w
b110000010001010000000000000001 )
b110000010001010000000000000001 /
b110000010001010000000000000001 0
b110000010001010000000000000001 M
b100 .
b11000 X
b11000 s
b11000 u
b10100 U
b10100 o
b10100 q
b10100 t
b10000 (
b10000 7
b10000 Y
b10000 p
b10000 {
1$
#65000
0$
#70000
b1 T
b1 ~
b1 #"
02
b1 #
b1 *
b1 -
b1 <
b1 [
b1 _
b1 |
b110 =
b110 C
b110 F
b110 K
b110 \
b0 Q
b0 ]
b0 )"
06
04
b0 :
b0 @
b0 H
b0 L
b0 a
0;
1A
b1 B
b1 E
b1 I
b1000001 J
b0 O
b0 $"
b0 ,"
b11000 W
b11000 y
b11000 z
b100 ?
b100 G
b10100000000000000000000100 x
b101 !"
b0 ""
b0 *"
b0 !
b0 &
b0 ,
b0 3
b0 P
b0 %"
b0 '"
b11000 V
b11000 v
b11000 w
b10000101000000000000000000001 )
b10000101000000000000000000001 /
b10000101000000000000000000001 0
b10000101000000000000000000001 M
b101 .
b11100 X
b11100 s
b11100 u
b11000 U
b11000 o
b11000 q
b11000 t
b10100 (
b10100 7
b10100 Y
b10100 p
b10100 {
1$
#75000
0$
#80000
b10 =
b10 C
b10 F
b10 K
b10 \
b100000000000000000001 T
b100000000000000000001 ~
b100000000000000000001 #"
bx '
bx +
bx 1
bx N
bx }
14
15
0A
b100 B
b100 E
b100 I
b100000000000000000001 #
b100000000000000000001 *
b100000000000000000001 -
b100000000000000000001 <
b100000000000000000001 [
b100000000000000000001 _
b100000000000000000001 |
b100100000100 J
b10000010000000 S
b10000010000000 m
b10000010000000 r
b1 Q
b1 ]
b1 )"
b100000100000 Z
b100000100000 e
b100000100000 l
b100000100000 ("
b100000000000000000000 R
b100000000000000000000 ^
b100000000000000000000 &"
b1 !
b1 &
b1 ,
b1 3
b1 P
b1 %"
b1 '"
b1 O
b1 $"
b1 ,"
b11100 W
b11100 y
b11100 z
b0 ?
b0 G
b100000 >
b100000 D
b100010000010000010000000 x
b1 !"
b10 ""
b10 *"
b1 +"
b100000100000 c
b100000100000 g
b1000001000000000000000000000 d
b1000001000000000000000000000 i
b100000100000 b
b100000100000 k
b100000100000 `
b100000100000 f
b100000100000 h
b100000100000 j
b11100 V
b11100 v
b11100 w
b1000100000100000100000 )
b1000100000100000100000 /
b1000100000100000100000 0
b1000100000100000100000 M
b110 .
b10000010011100 X
b10000010011100 s
b10000010011100 u
b11100 U
b11100 o
b11100 q
b11100 t
b11000 (
b11000 7
b11000 Y
b11000 p
b11000 {
1$
#85000
0$
#90000
b111100000000010000000000010000 '
b111100000000010000000000010000 +
b111100000000010000000000010000 1
b111100000000010000000000010000 N
b111100000000010000000000010000 }
05
1;
b0 B
b0 E
b0 I
b10 T
b10 ~
b10 #"
12
b100010000000 J
b10 =
b10 C
b10 F
b10 K
b10 \
b10 #
b10 *
b10 -
b10 <
b10 [
b10 _
b10 |
b100 S
b100 m
b100 r
b1 Z
b1 e
b1 l
b1 ("
b10 O
b10 $"
b10 ,"
b100000 W
b100000 y
b100000 z
b1000 ?
b1000 G
b1 >
b1 D
b1000010000000000000000100 x
b10 !"
b0 +"
b1 c
b1 g
b10000000000000000 d
b10000000000000000 i
b1 b
b1 k
b1 `
b1 f
b1 h
b1 j
b1 R
b1 ^
b1 &"
b100000 V
b100000 v
b100000 w
b100000010000100000000000000001 )
b100000010000100000000000000001 /
b100000010000100000000000000001 0
b100000010000100000000000000001 M
b111 .
b100100 X
b100100 s
b100100 u
b100000 U
b100000 o
b100000 q
b100000 t
b11100 (
b11100 7
b11100 Y
b11100 p
b11100 {
1$
#95000
0$
#100000
b111 =
b111 C
b111 F
b111 K
b111 \
b111100000000010000000000010000 '
b111100000000010000000000010000 +
b111100000000010000000000010000 1
b111100000000010000000000010000 N
b111100000000010000000000010000 }
15
0;
b100 B
b100 E
b100 I
b1 T
b1 ~
b1 #"
b100100000100 J
02
b1 #
b1 *
b1 -
b1 <
b1 [
b1 _
b1 |
b1010000010101000 S
b1010000010101000 m
b1010000010101000 r
b1011 Q
b1011 ]
b1011 )"
b10100000101010 Z
b10100000101010 e
b10100000101010 l
b10100000101010 ("
b101 O
b101 $"
b101 ,"
b100100 W
b100100 y
b100100 z
b0 ?
b0 G
b101010 >
b101010 D
b1000011001010000010101000 x
b11 ""
b11 *"
b101 +"
b10100000101010 c
b10100000101010 g
b101000001010100000000000000000 d
b101000001010100000000000000000 i
b10100000101010 b
b10100000101010 k
b10100000101010 `
b10100000101010 f
b10100000101010 h
b10100000101010 j
b10 R
b10 ^
b10 &"
b1011 !
b1011 &
b1011 ,
b1011 3
b1011 P
b1011 %"
b1011 '"
b100100 V
b100100 v
b100100 w
b10000110010100000101010 )
b10000110010100000101010 /
b10000110010100000101010 0
b10000110010100000101010 M
b1000 .
b1010000011001100 X
b1010000011001100 s
b1010000011001100 u
b100100 U
b100100 o
b100100 q
b100100 t
b100000 (
b100000 7
b100000 Y
b100000 p
b100000 {
1$
#105000
0$
#110000
16
b0 T
b0 ~
b0 #"
04
05
1A
b1 B
b1 E
b1 I
12
b0 #
b0 *
b0 -
b0 <
b0 [
b0 _
b0 |
b1000001 J
b110 =
b110 C
b110 F
b110 K
b110 \
b11111111111111111111111111101000 S
b11111111111111111111111111101000 m
b11111111111111111111111111101000 r
b1 Q
b1 ]
b1 )"
b11111111111111111111111111111010 Z
b11111111111111111111111111111010 e
b11111111111111111111111111111010 l
b11111111111111111111111111111010 ("
b1 R
b1 ^
b1 &"
b1 !
b1 &
b1 ,
b1 3
b1 P
b1 %"
b1 '"
b100 O
b100 $"
b100 ,"
b10000 W
b10000 y
b10000 z
b100 ?
b100 G
b111010 >
b111010 D
b10100100111111111111101000 x
b101 !"
b100 ""
b100 *"
b11111 +"
b11111111111111111111111111111010 c
b11111111111111111111111111111010 g
b11111111111110100000000000000000 d
b11111111111110100000000000000000 i
b1111111111111010 b
b1111111111111010 k
b1111111111111010 `
b1111111111111010 f
b1111111111111010 h
b1111111111111010 j
b10000 V
b10000 v
b10000 w
b10000101001001111111111111010 )
b10000101001001111111111111010 /
b10000101001001111111111111010 0
b10000101001001111111111111010 M
b1001 .
b10000 X
b10000 s
b10000 u
b101000 U
b101000 o
b101000 q
b101000 t
b100100 (
b100100 7
b100100 Y
b100100 p
b100100 {
1$
#115000
0$
#120000
b0 =
b0 C
b0 F
b0 K
b0 \
06
b0 T
b0 ~
b0 #"
14
b1 :
b1 @
b1 H
b1 L
b1 a
1;
0A
b10 B
b10 E
b10 I
02
b0 #
b0 *
b0 -
b0 <
b0 [
b0 _
b0 |
b101010000010 J
b100 S
b100 m
b100 r
b1 Z
b1 e
b1 l
b1 ("
b10 R
b10 ^
b10 &"
b101 O
b101 $"
b101 ,"
b10100 W
b10100 y
b10100 z
b1100 ?
b1100 G
b1 >
b1 D
b1000101000000000000000100 x
b10 !"
b101 ""
b101 *"
b0 +"
b1 c
b1 g
b10000000000000000 d
b10000000000000000 i
b1 b
b1 k
b1 `
b1 f
b1 h
b1 j
b10100 V
b10100 v
b10100 w
b110000010001010000000000000001 )
b110000010001010000000000000001 /
b110000010001010000000000000001 0
b110000010001010000000000000001 M
b100 .
b11000 X
b11000 s
b11000 u
b10100 U
b10100 o
b10100 q
b10100 t
b10000 (
b10000 7
b10000 Y
b10000 p
b10000 {
1$
#125000
0$
#130000
16
12
b110 =
b110 C
b110 F
b110 K
b110 \
b0 Q
b0 ]
b0 )"
04
b0 :
b0 @
b0 H
b0 L
b0 a
0;
1A
b1 B
b1 E
b1 I
b1000001 J
b0 R
b0 ^
b0 &"
b0 O
b0 $"
b0 ,"
b11100 W
b11100 y
b11100 z
b100 ?
b100 G
b10100000000000000000000100 x
b101 !"
b0 ""
b0 *"
b0 !
b0 &
b0 ,
b0 3
b0 P
b0 %"
b0 '"
b11100 V
b11100 v
b11100 w
b10000101000000000000000000001 )
b10000101000000000000000000001 /
b10000101000000000000000000001 0
b10000101000000000000000000001 M
b101 .
b11100 X
b11100 s
b11100 u
b11000 U
b11000 o
b11000 q
b11000 t
b10100 (
b10100 7
b10100 Y
b10100 p
b10100 {
1$
#135000
0$
